leetcodecli/__init__.py
leetcodecli/cli.py
leetcodecli/header.html
leetcode_cli-0.1.0.dist-info/LICENSE
leetcode_cli-0.1.0.dist-info/METADATA
leetcode_cli-0.1.0.dist-info/WHEEL
leetcode_cli-0.1.0.dist-info/entry_points.txt
leetcode_cli-0.1.0.dist-info/top_level.txt
leetcode_cli-0.1.0.dist-info/RECORD
