Metadata-Version: 2.1
Name: leetcode-cli
Version: 0.1.0
Summary: LeetCode CLI
Home-page: https://github.com/chenpengcheng/cli
Author: Pengcheng Chen
Author-email: pengcheng.chen@gmail.com
Keywords: leetcode
Classifier: Programming Language :: Python :: 3
Classifier: License :: OSI Approved :: MIT License
Classifier: Operating System :: OS Independent
License-File: LICENSE
Requires-Dist: ascii-graph
Requires-Dist: browser-cookie3
Requires-Dist: beautifulsoup4
Requires-Dist: pyexecjs
Requires-Dist: requests
